gaussianrunner/__init__.py
gaussianrunner/analyst.py
gaussianrunner/mpi.py
gaussianrunner/runner.py
gaussianrunner-1.0.34.dist-info/LICENSE
gaussianrunner-1.0.34.dist-info/METADATA
gaussianrunner-1.0.34.dist-info/WHEEL
gaussianrunner-1.0.34.dist-info/entry_points.txt
gaussianrunner-1.0.34.dist-info/top_level.txt
gaussianrunner-1.0.34.dist-info/RECORD
