Metadata-Version: 2.1
Name: gaussianrunner
Version: 1.0.34
Summary: A script to run Gaussian automatically.
Author-email: Jinzhe Zeng <jinzhe.zeng@rutgers.edu>
License: GNU LESSER GENERAL PUBLIC LICENSE
Project-URL: homepage, https://github.com/njzjz/gaussianrunner
Project-URL: repository, https://github.com/njzjz/gaussianrunner
Keywords: gaussian
Classifier: Natural Language :: English
Classifier: Operating System :: POSIX :: Linux
Classifier: Operating System :: Microsoft :: Windows
Classifier: Programming Language :: Python :: 3.6
Classifier: Programming Language :: Python :: 3.7
Classifier: Programming Language :: Python :: 3.8
Classifier: Programming Language :: Python :: 3.9
Classifier: Programming Language :: Python :: 3.10
Classifier: Programming Language :: Python :: 3.11
Classifier: Topic :: Scientific/Engineering :: Chemistry
Classifier: Topic :: Software Development :: Libraries :: Python Modules
Classifier: Topic :: Software Development :: Version Control :: Git
Requires-Python: >=3.7
License-File: LICENSE
Requires-Dist: numpy
Requires-Dist: coloredlogs
Requires-Dist: openbabel-wheel
Requires-Dist: importlib-metadata >=1.4 ; python_version < "3.8"
Provides-Extra: mpi
Requires-Dist: mpi4py ; extra == 'mpi'
Provides-Extra: test
Requires-Dist: pytest-sugar ; extra == 'test'
Requires-Dist: pytest-cov ; extra == 'test'
Requires-Dist: fakegaussian >=0.0.2 ; extra == 'test'
